pyturbo/__init__.py
pyturbo/pipeline.py
pyturbo/resource.py
pyturbo/runtime.py
pyturbo/stage.py
pyturbo/system.py
pyturbo/task.py
pyturbo/utils.py
pyturbo/worker.py
py_turbo-0.7.0.dist-info/LICENSE
py_turbo-0.7.0.dist-info/METADATA
py_turbo-0.7.0.dist-info/WHEEL
py_turbo-0.7.0.dist-info/top_level.txt
py_turbo-0.7.0.dist-info/RECORD
