Metadata-Version: 2.1
Name: py-turbo
Version: 0.7.0
Summary: A pipeline system for efficient execution.
Home-page: https://github.com/CMU-INF-DIVA/pyturbo
Author: Lijun Yu
Author-email: lijun@lj-y.com
License: GPL
Requires-Python: >=3.7
License-File: LICENSE
Requires-Dist: tqdm
Requires-Dist: GPUtil
Requires-Dist: psutil
